{"64":[{"Status":"0","Action":"Mario Jumps","X":"596.1632","Y":"223.0","Time":"64"}],"128":[{"Status":"0","Action":"Long Jump","X":"1305.1897","Y":"223.0","Time":"128"}],"192":[{"Status":"0","Action":"Mario Jumps","X":"1990.7263","Y":"239.0","Time":"192"}],"194":[{"Status":"0","Action":"Low Jump","X":"2010.637","Y":"220.0","Time":"194"},{"Status":"0","Action":"Short Jump","X":"2020.7466","Y":"223.0","Time":"194"}],"258":[{"Status":"0","Action":"Long Jump","X":"2712.4634","Y":"223.0","Time":"258"}],"68":[{"Status":"0","Action":"Low Jump","X":"639.77563","Y":"175.5","Time":"68"}],"8":[{"Status":"0","Action":"Mario Jumps","X":"29.05587","Y":"223.0","Time":"8"}],"10":[{"Status":"0","Action":"Low Jump","X":"41.754356","Y":"196.4","Time":"10"}],"76":[{"Status":"0","Action":"Long Jump","X":"737.9312","Y":"223.0","Time":"76"}],"78":[{"Status":"0","Action":"Mario Jumps","X":"748.83875","Y":"223.0","Time":"78"}],"270":[{"Status":"0","Action":"Mario Jumps","X":"2832.4607","Y":"223.0","Time":"270"}],"80":[{"Status":"0","Action":"Low Jump","X":"770.6543","Y":"196.4","Time":"80"}],"272":[{"Status":"0","Action":"Low Jump","X":"2854.2786","Y":"196.4","Time":"272"}],"18":[{"Status":"0","Action":"Long Jump","X":"117.363594","Y":"223.0","Time":"18"}],"210":[{"Status":"0","Action":"High Jump","X":"2179.041","Y":"212.4","Time":"210"}],"88":[{"Status":"0","Action":"Long Jump","X":"868.82965","Y":"223.0","Time":"88"}],"152":[{"Status":"0","Action":"Mario Jumps","X":"1556.098","Y":"223.0","Time":"152"}],"280":[{"Status":"0","Action":"Long Jump","X":"2952.459","Y":"223.0","Time":"280"}],"154":[{"Status":"0","Action":"Low Jump","X":"1577.9161","Y":"196.4","Time":"154"}],"224":[{"Status":"0","Action":"Mario Jumps","X":"2330.862","Y":"223.0","Time":"224"}],"162":[{"Status":"0","Action":"Long Jump","X":"1676.0977","Y":"223.0","Time":"162"}],"226":[{"Status":"0","Action":"Low Jump","X":"2352.6343","Y":"196.4","Time":"226"}],"104":[{"Status":"0","Action":"Mario Jumps","X":"1032.4633","Y":"223.0","Time":"104"}],"106":[{"Status":"0","Action":"Low Jump","X":"1054.2814","Y":"196.4","Time":"106"}],"234":[{"Status":"0","Action":"Long Jump","X":"2450.703","Y":"223.0","Time":"234"}],"172":[{"Status":"0","Action":"Mario Jumps","X":"1774.2792","Y":"223.0","Time":"172"}],"112":[{"Status":"0","Action":"Long Jump","X":"1130.6448","Y":"207.0","Time":"112"}],"176":[{"Status":"0","Action":"Low Jump","X":"1817.9154","Y":"175.5","Time":"176"}],"306":[{"Status":"0","Action":"Mario Jumps","X":"3225.1882","Y":"223.0","Time":"306"}],"52":[{"Status":"0","Action":"Mario Jumps","X":"465.45016","Y":"223.0","Time":"52"}],"54":[{"Status":"0","Action":"Low Jump","X":"487.21423","Y":"196.4","Time":"54"}],"118":[{"Status":"0","Action":"Mario Jumps","X":"1185.1901","Y":"223.0","Time":"118"}],"183":[{"Status":"0","Action":"Long Jump","X":"1905.1879","Y":"207.0","Time":"183"}],"120":[{"Status":"0","Action":"Low Jump","X":"1207.0082","Y":"196.4","Time":"120"}],"248":[{"Status":"0","Action":"Mario Jumps","X":"2592.4731","Y":"223.0","Time":"248"}],"312":[{"Status":"0","Action":"High Jump","X":"3290.6433","Y":"162.2","Time":"312"}],"249":[{"Status":"0","Action":"Fall Kill","X":"2603.3809","Y":"209.7","Time":"249"}],"250":[{"Status":"0","Action":"Low Jump","X":"2614.2886","Y":"196.4","Time":"250"}],"60":[{"Status":"0","Action":"Long Jump","X":"563.4629","Y":"207.0","Time":"60"}],"317":[{"Status":"0","Action":"Long Jump","X":"3356.0984","Y":"191.0","Time":"317"}]}