{"38":[{"Status":"0","Action":"Long Jump","X":"307.06372","Y":"223.0","Time":"38"}],"40":[{"Status":"0","Action":"Mario Jumps","X":"314.9667","Y":"223.0","Time":"40"}],"72":[{"Status":"0","Action":"Mario Jumps","X":"640.31946","Y":"223.0","Time":"72"}],"298":[{"Status":"0","Action":"Stomp Kill","X":"3116.1055","Y":"227.0","Time":"298"}],"76":[{"Status":"0","Action":"Low Jump","X":"683.7382","Y":"175.5","Time":"76"}],"47":[{"Status":"0","Action":"High Jump","X":"377.76617","Y":"158.4","Time":"47"}],"79":[{"Status":"0","Action":"Long Jump","X":"727.23804","Y":"175.0","Time":"79"}],"210":[{"Status":"0","Action":"Mario Jumps","X":"2145.1885","Y":"223.0","Time":"210"}],"274":[{"Status":"0","Action":"Mario Jumps","X":"2843.376","Y":"223.0","Time":"274"}],"276":[{"Status":"0","Action":"Low Jump","X":"2865.1943","Y":"196.4","Time":"276"}],"214":[{"Status":"0","Action":"Low Jump","X":"2188.8252","Y":"175.5","Time":"214"}],"55":[{"Status":"0","Action":"Long Jump","X":"468.9591","Y":"223.0","Time":"55"}],"282":[{"Status":"0","Action":"Long Jump","X":"2941.5586","Y":"207.0","Time":"282"}],"28":[{"Status":"0","Action":"Mario Jumps","X":"205.90295","Y":"223.0","Time":"28"}],"284":[{"Status":"0","Action":"Stomp Kill","X":"2963.377","Y":"219.61917","Time":"284"}],"30":[{"Status":"0","Action":"Low Jump","X":"224.92691","Y":"196.4","Time":"30"}],"222":[{"Status":"0","Action":"Long Jump","X":"2287.0078","Y":"223.0","Time":"222"}],"287":[{"Status":"0","Action":"Fall Kill","X":"2985.1953","Y":"194.49918","Time":"287"}]}