{"129":[{"Status":"0","Action":"High Jump","X":"1294.3419","Y":"158.4","Time":"129"}],"194":[{"Status":"0","Action":"Long Jump","X":"2003.379","Y":"223.0","Time":"194"}],"131":[{"Status":"0","Action":"Long Jump","X":"1327.0511","Y":"159.0","Time":"131"}],"133":[{"Status":"0","Action":"Coins Collected","X":"1337.3555","Y":"159.0","Time":"133"}],"134":[{"Status":"0","Action":"Mario Jumps","X":"1347.1263","Y":"159.0","Time":"134"}],"136":[{"Status":"0","Action":"Low Jump","X":"1367.0299","Y":"132.4","Time":"136"}],"73":[{"Status":"0","Action":"Stomp Kill","X":"705.2099","Y":"211.0","Time":"73"}],"148":[{"Status":"0","Action":"Long Jump","X":"1503.157","Y":"223.0","Time":"148"}],"85":[{"Status":"0","Action":"Coins Collected","X":"824.5954","Y":"159.0","Time":"85"}],"86":[{"Status":"0","Action":"Mario Jumps","X":"834.3699","Y":"159.0","Time":"86"}],"214":[{"Status":"0","Action":"Mario Jumps","X":"2210.6448","Y":"223.0","Time":"214"}],"88":[{"Status":"0","Action":"Low Jump","X":"854.27954","Y":"132.4","Time":"88"}],"216":[{"Status":"0","Action":"Low Jump","X":"2232.4626","Y":"196.4","Time":"216"}],"28":[{"Status":"0","Action":"Fall Kill","X":"207.63695","Y":"223.0","Time":"28"}],"284":[{"Status":"0","Action":"Mario Jumps","X":"2974.285","Y":"223.0","Time":"284"}],"286":[{"Status":"0","Action":"Low Jump","X":"2996.1033","Y":"196.4","Time":"286"}],"224":[{"Status":"0","Action":"Long Jump","X":"2330.6433","Y":"223.0","Time":"224"}],"100":[{"Status":"0","Action":"Long Jump","X":"990.4247","Y":"223.0","Time":"100"}],"166":[{"Status":"0","Action":"Mario Jumps","X":"1687.2291","Y":"223.0","Time":"166"}],"294":[{"Status":"0","Action":"Long Jump","X":"3094.286","Y":"223.0","Time":"294"}],"168":[{"Status":"0","Action":"Low Jump","X":"1709.0013","Y":"196.4","Time":"168"}],"108":[{"Status":"0","Action":"Mario Jumps","X":"1065.897","Y":"223.0","Time":"108"}],"110":[{"Status":"0","Action":"Low Jump","X":"1087.5681","Y":"196.4","Time":"110"}],"176":[{"Status":"0","Action":"Long Jump","X":"1807.0692","Y":"223.0","Time":"176"}],"178":[{"Status":"0","Action":"Mario Jumps","X":"1817.9716","Y":"223.0","Time":"178"}],"306":[{"Status":"0","Action":"Mario Jumps","X":"3214.2869","Y":"223.0","Time":"306"}],"179":[{"Status":"0","Action":"Low Jump","X":"1828.8746","Y":"220.0","Time":"179"},{"Status":"0","Action":"Short Jump","X":"1839.7783","Y":"223.0","Time":"179"}],"308":[{"Status":"0","Action":"Low Jump","X":"3236.1052","Y":"196.4","Time":"308"}],"118":[{"Status":"0","Action":"Long Jump","X":"1185.3861","Y":"223.0","Time":"118"}],"184":[{"Status":"0","Action":"Mario Jumps","X":"1883.3986","Y":"223.0","Time":"184"}],"248":[{"Status":"0","Action":"Coins Collected","X":"2581.5544","Y":"223.0","Time":"248"}],"122":[{"Status":"0","Action":"Mario Jumps","X":"1218.0554","Y":"223.0","Time":"122"}],"186":[{"Status":"0","Action":"Low Jump","X":"1905.211","Y":"196.4","Time":"186"}],"316":[{"Status":"0","Action":"Long Jump","X":"3334.2878","Y":"223.0","Time":"316"}]}