{"130":[{"Status":"0","Action":"Mario Jumps","X":"1294.4016","Y":"223.0","Time":"130"}],"258":[{"Status":"0","Action":"Mario Jumps","X":"2690.649","Y":"191.0","Time":"258"}],"131":[{"Status":"0","Action":"Coins Collected","X":"1305.2974","Y":"209.7","Time":"131"}],"132":[{"Status":"0","Action":"Low Jump","X":"1316.1946","Y":"196.4","Time":"132"}],"260":[{"Status":"0","Action":"Low Jump","X":"2712.4673","Y":"164.4","Time":"260"}],"8":[{"Status":"0","Action":"Mario Jumps","X":"29.05587","Y":"223.0","Time":"8"}],"264":[{"Status":"0","Action":"Short Jump","X":"2767.0132","Y":"159.0","Time":"264"}],"266":[{"Status":"0","Action":"Mario Jumps","X":"2777.9224","Y":"159.0","Time":"266"}],"12":[{"Status":"0","Action":"Low Jump","X":"56.348824","Y":"175.5","Time":"12"}],"140":[{"Status":"0","Action":"Long Jump","X":"1414.314","Y":"223.0","Time":"140"}],"268":[{"Status":"0","Action":"Low Jump","X":"2799.7407","Y":"132.4","Time":"268"}],"19":[{"Status":"0","Action":"Long Jump","X":"126.93359","Y":"207.0","Time":"19"}],"280":[{"Status":"0","Action":"Long Jump","X":"2941.56","Y":"223.0","Time":"280"}],"26":[{"Status":"0","Action":"Mario Jumps","X":"186.93822","Y":"239.0","Time":"26"}],"28":[{"Status":"0","Action":"Low Jump","X":"207.63695","Y":"212.4","Time":"28"}],"156":[{"Status":"0","Action":"Mario Jumps","X":"1577.9225","Y":"223.0","Time":"156"}],"284":[{"Status":"0","Action":"Mario Jumps","X":"2974.2876","Y":"223.0","Time":"284"}],"158":[{"Status":"0","Action":"Low Jump","X":"1599.7395","Y":"196.4","Time":"158"}],"286":[{"Status":"0","Action":"Low Jump","X":"2996.106","Y":"196.4","Time":"286"}],"34":[{"Status":"0","Action":"Long Jump","X":"281.62195","Y":"223.0","Time":"34"},{"Status":"0","Action":"Stomp Kill","X":"281.62195","Y":"211.0","Time":"34"}],"290":[{"Status":"0","Action":"Fall Kill","X":"3039.7427","Y":"186.20258","Time":"290"}],"35":[{"Status":"0","Action":"Coins Collected","X":"281.62195","Y":"211.0","Time":"35"}],"166":[{"Status":"0","Action":"Long Jump","X":"1697.9183","Y":"223.0","Time":"166"}],"294":[{"Status":"0","Action":"Long Jump","X":"3094.2886","Y":"223.0","Time":"294"}],"168":[{"Status":"0","Action":"Mario Jumps","X":"1708.8273","Y":"223.0","Time":"168"}],"296":[{"Status":"0","Action":"Stomp Kill","X":"3116.107","Y":"220.0","Time":"296"}],"170":[{"Status":"0","Action":"Low Jump","X":"1730.6451","Y":"196.4","Time":"170"}],"298":[{"Status":"0","Action":"High Jump","X":"3127.016","Y":"204.8","Time":"298"}],"301":[{"Status":"0","Action":"Shell Kill","X":"3170.6528","Y":"189.45618","Time":"301"}],"178":[{"Status":"0","Action":"Long Jump","X":"1828.8263","Y":"223.0","Time":"178"}],"58":[{"Status":"0","Action":"Mario Jumps","X":"530.7738","Y":"223.0","Time":"58"}],"186":[{"Status":"0","Action":"Fall Kill","X":"1905.1897","Y":"223.0","Time":"186"},{"Status":"0","Action":"Mario Jumps","X":"1905.1897","Y":"223.0","Time":"186"}],"60":[{"Status":"0","Action":"Low Jump","X":"552.56506","Y":"196.4","Time":"60"}],"188":[{"Status":"0","Action":"Low Jump","X":"1927.0078","Y":"196.4","Time":"188"}],"320":[{"Status":"0","Action":"Mario Jumps","X":"3367.018","Y":"223.0","Time":"320"}],"322":[{"Status":"0","Action":"Low Jump","X":"3388.8364","Y":"196.4","Time":"322"}],"196":[{"Status":"0","Action":"Long Jump","X":"2025.1893","Y":"223.0","Time":"196"}],"69":[{"Status":"0","Action":"Long Jump","X":"661.58545","Y":"239.0","Time":"69"}],"198":[{"Status":"0","Action":"Mario Jumps","X":"2036.0984","Y":"223.0","Time":"198"}],"72":[{"Status":"0","Action":"Mario Jumps","X":"683.397","Y":"239.0","Time":"72"}],"74":[{"Status":"0","Action":"Low Jump","X":"705.2099","Y":"212.4","Time":"74"}],"330":[{"Status":"0","Action":"Long Jump","X":"3487.019","Y":"223.0","Time":"330"}],"205":[{"Status":"0","Action":"High Jump","X":"2112.4624","Y":"158.4","Time":"205"}],"80":[{"Status":"0","Action":"Long Jump","X":"780.9623","Y":"223.0","Time":"80"}],"84":[{"Status":"0","Action":"Mario Jumps","X":"810.64545","Y":"223.0","Time":"84"}],"213":[{"Status":"0","Action":"Long Jump","X":"2210.645","Y":"223.0","Time":"213"}],"86":[{"Status":"0","Action":"Low Jump","X":"830.95135","Y":"196.4","Time":"86"}],"217":[{"Status":"0","Action":"Fall Kill","X":"2243.3726","Y":"223.0","Time":"217"}],"92":[{"Status":"0","Action":"Long Jump","X":"899.6609","Y":"223.0","Time":"92"}],"94":[{"Status":"0","Action":"Stomp Kill","X":"919.6045","Y":"220.0","Time":"94"}],"98":[{"Status":"0","Action":"Bumping Brick Block","X":"950.2247","Y":"191.5","Time":"98"}],"100":[{"Status":"0","Action":"High Jump","X":"970.9961","Y":"172.0","Time":"100"}],"104":[{"Status":"0","Action":"High Jump","X":"1013.14655","Y":"148.4","Time":"104"}],"246":[{"Status":"0","Action":"Mario Jumps","X":"2559.7388","Y":"223.0","Time":"246"}],"250":[{"Status":"0","Action":"Low Jump","X":"2603.3755","Y":"175.5","Time":"250"},{"Status":"0","Action":"Bumping Question Block","X":"2614.2847","Y":"175.5","Time":"250"}],"251":[{"Status":"0","Action":"Short Jump","X":"2625.1938","Y":"175.0","Time":"251"}]}